stashokta/__init__.py
stashokta/aws_auth.py
stashokta/okta_auth.py
stashokta/okta_awscli.py
stashokta/version.py
stash_okta-0.4.7.dist-info/LICENSE
stash_okta-0.4.7.dist-info/METADATA
stash_okta-0.4.7.dist-info/WHEEL
stash_okta-0.4.7.dist-info/entry_points.txt
stash_okta-0.4.7.dist-info/top_level.txt
stash_okta-0.4.7.dist-info/RECORD
